pytree/__init__.py
pytree/cli.py
pytree_cli-0.1.dist-info/LICENSE
pytree_cli-0.1.dist-info/METADATA
pytree_cli-0.1.dist-info/WHEEL
pytree_cli-0.1.dist-info/entry_points.txt
pytree_cli-0.1.dist-info/top_level.txt
pytree_cli-0.1.dist-info/RECORD
